limits/__init__.py
limits/_version.py
limits/errors.py
limits/limits.py
limits/py.typed
limits/strategies.py
limits/typing.py
limits/util.py
limits/version.py
limits/aio/__init__.py
limits/aio/strategies.py
limits/aio/storage/__init__.py
limits/aio/storage/base.py
limits/aio/storage/etcd.py
limits/aio/storage/memcached.py
limits/aio/storage/memory.py
limits/aio/storage/mongodb.py
limits/aio/storage/redis/__init__.py
limits/aio/storage/redis/bridge.py
limits/aio/storage/redis/coredis.py
limits/aio/storage/redis/redispy.py
limits/aio/storage/redis/valkey.py
limits/resources/redis/lua_scripts/acquire_moving_window.lua
limits/resources/redis/lua_scripts/acquire_sliding_window.lua
limits/resources/redis/lua_scripts/clear_keys.lua
limits/resources/redis/lua_scripts/incr_expire.lua
limits/resources/redis/lua_scripts/moving_window.lua
limits/resources/redis/lua_scripts/sliding_window.lua
limits/storage/__init__.py
limits/storage/base.py
limits/storage/etcd.py
limits/storage/memcached.py
limits/storage/memory.py
limits/storage/mongodb.py
limits/storage/redis.py
limits/storage/redis_cluster.py
limits/storage/redis_sentinel.py
limits/storage/registry.py
limits-4.7.dist-info/licenses/LICENSE.txt
limits-4.7.dist-info/METADATA
limits-4.7.dist-info/WHEEL
limits-4.7.dist-info/top_level.txt
limits-4.7.dist-info/RECORD
