Metadata-Version: 2.4
Name: limits
Version: 4.7
Summary: Rate limiting utilities
Home-page: https://limits.readthedocs.org
Author: Ali-Akber Saifee
Author-email: ali@indydevs.org
License: MIT
Project-URL: Source, https://github.com/alisaifee/limits
Classifier: Development Status :: 5 - Production/Stable
Classifier: Intended Audience :: Developers
Classifier: License :: OSI Approved :: MIT License
Classifier: Operating System :: MacOS
Classifier: Operating System :: POSIX :: Linux
Classifier: Operating System :: OS Independent
Classifier: Topic :: Software Development :: Libraries :: Python Modules
Classifier: Programming Language :: Python :: 3.10
Classifier: Programming Language :: Python :: 3.11
Classifier: Programming Language :: Python :: 3.12
Classifier: Programming Language :: Python :: 3.13
Classifier: Programming Language :: Python :: Implementation :: PyPy
Requires-Python: >=3.10
License-File: LICENSE.txt
Requires-Dist: deprecated>=1.2
Requires-Dist: packaging<25,>=21
Requires-Dist: typing_extensions
Provides-Extra: redis
Requires-Dist: redis!=4.5.2,!=4.5.3,<6.0.0,>3; extra == "redis"
Provides-Extra: rediscluster
Requires-Dist: redis!=4.5.2,!=4.5.3,>=4.2.0; extra == "rediscluster"
Provides-Extra: memcached
Requires-Dist: pymemcache<5.0.0,>3; extra == "memcached"
Provides-Extra: mongodb
Requires-Dist: pymongo<5,>4.1; extra == "mongodb"
Provides-Extra: etcd
Requires-Dist: etcd3; extra == "etcd"
Provides-Extra: valkey
Requires-Dist: valkey>=6; extra == "valkey"
Provides-Extra: async-redis
Requires-Dist: coredis<5,>=3.4.0; extra == "async-redis"
Provides-Extra: async-memcached
Requires-Dist: emcache>=0.6.1; python_version < "3.11" and extra == "async-memcached"
Requires-Dist: emcache>=1; (python_version >= "3.11" and python_version < "3.13.0") and extra == "async-memcached"
Provides-Extra: async-mongodb
Requires-Dist: motor<4,>=3; extra == "async-mongodb"
Provides-Extra: async-etcd
Requires-Dist: aetcd; extra == "async-etcd"
Provides-Extra: async-valkey
Requires-Dist: valkey>=6; extra == "async-valkey"
Provides-Extra: all
Requires-Dist: redis!=4.5.2,!=4.5.3,<6.0.0,>3; extra == "all"
Requires-Dist: redis!=4.5.2,!=4.5.3,>=4.2.0; extra == "all"
Requires-Dist: pymemcache<5.0.0,>3; extra == "all"
Requires-Dist: pymongo<5,>4.1; extra == "all"
Requires-Dist: etcd3; extra == "all"
Requires-Dist: valkey>=6; extra == "all"
Requires-Dist: coredis<5,>=3.4.0; extra == "all"
Requires-Dist: emcache>=0.6.1; python_version < "3.11" and extra == "all"
Requires-Dist: emcache>=1; (python_version >= "3.11" and python_version < "3.13.0") and extra == "all"
Requires-Dist: motor<4,>=3; extra == "all"
Requires-Dist: aetcd; extra == "all"
Requires-Dist: valkey>=6; extra == "all"
Dynamic: author
Dynamic: author-email
Dynamic: classifier
Dynamic: description
Dynamic: home-page
Dynamic: license
Dynamic: license-file
Dynamic: project-url
Dynamic: provides-extra
Dynamic: requires-dist
Dynamic: requires-python
Dynamic: summary
